Metadata-Version: 2.1
Name: anyrun-legacy
Version: 1.9.6
Summary: This is the official Python client library for ANY.RUN. Automate management of ANY.RUN REST endpoints
Home-page: https://github.com/anyrun/anyrun-sdk
Author: Semen Shalnev, Danila Korolev
Author-email: anyrun-integrations@any.run
License: UNKNOWN
Platform: UNKNOWN
Classifier: Programming Language :: Python :: 3.5
Classifier: Programming Language :: Python :: 3.6
Classifier: Programming Language :: Python :: 3.7
Classifier: Programming Language :: Python :: 3.8
Classifier: Topic :: Software Development :: Libraries
Classifier: Typing :: Typed
Requires-Python: >=3.5
Requires-Dist: aiohttp (==3.6.3)
Requires-Dist: aiofiles (==0.6.0)
Requires-Dist: typing-extensions (==3.10.0.2)
Requires-Dist: requests (==2.25.1)
